cone/ConeExit.py
cone/__init__.py
cone/project.py
cone/commands/__init__.py
cone/commands/deploy.py
cone/commands/revert.py
cone/commands/test.py
cone/commands/version.py
cone/server/ConeCore.py
cone/server/Server.py
cone/server/__init__.py
console_cone/__init__.py
console_cone/__main__.py
console_cone/get_parser.py
console_cone/main.py
tests/__init__.py
tests/cone/__init__.py
tests/cone/test_project.py
tests/cone/server/__init__.py
tests/cone/server/test_ConeCore.py
tests/console_cone/__init__.py
tests/console_cone/test_get_parser.py
cone-0.1.1.dist-info/METADATA
cone-0.1.1.dist-info/WHEEL
cone-0.1.1.dist-info/entry_points.txt
cone-0.1.1.dist-info/top_level.txt
cone-0.1.1.dist-info/RECORD
