Metadata-Version: 2.1
Name: cone
Version: 0.1.1
Summary: A tool to sync projects to Roblox Studio
Home-page: https://gitlab.com/rbx-cone/cone
Author: Olivier Trepanier
Author-email: olitrepanier@hotmail.com
License: UNKNOWN
Keywords: roblox
Platform: UNKNOWN
Requires-Dist: Flask
